mcp_wolfram_alpha/__init__.py
mcp_wolfram_alpha/server.py
mcp_wolfram_alpha/wolfram_client.py
wolfram_alpha_mcp_server-0.1.1.dist-info/licenses/LICENSE
wolfram_alpha_mcp_server-0.1.1.dist-info/METADATA
wolfram_alpha_mcp_server-0.1.1.dist-info/WHEEL
wolfram_alpha_mcp_server-0.1.1.dist-info/entry_points.txt
wolfram_alpha_mcp_server-0.1.1.dist-info/top_level.txt
wolfram_alpha_mcp_server-0.1.1.dist-info/RECORD
