Metadata-Version: 2.4
Name: wolfram-alpha-mcp-server
Version: 0.1.1
Summary: A MCP server to connect to wolfram alpha API.
Author-email: TerminalMan <84923604+SecretiveShell@users.noreply.github.com>
Requires-Python: >=3.13
License-File: LICENSE
Requires-Dist: asyncio>=3.4.3
Requires-Dist: httpx>=0.28.1
Requires-Dist: mcp>=1.6.0
Requires-Dist: wolframalpha>=5.1.3
Dynamic: license-file
